[
    [
      {"id": 0, "name": "Город"},
      {"id": 1, "name": "Астана" },
      {"id": 2, "name": "Алматы" },
      {"id": 3, "name": "Актюбинск" },
      {"id": 4, "name": "Шымкент" },
      {"id": 5, "name": "Талдыкорган" },
      {"id": 6, "name": "Кызылорда" },
      {"id": 7, "name": "Караганда" },
      {"id": 8, "name": "Павлодар" },
      {"id": 9, "name": "Усть-Каменегорск" },
      {"id": 10, "name": "Актау" },
      {"id": 11, "name": "Не указан" }
    ],

    [
      {"id": 0, "name": "Опыт работы"},
      {"id": 1, "name": "Нет опыта"},
      {"id": 2, "name": "От 1 года до 3 лет"},
      {"id": 3, "name": "От 3 до 6 лет"},
      {"id": 4, "name": "Более 6 лет"},
      {"id": 5, "name": "Не указан"}
    ],

    [
      {"id": 0, "name": "Тип занятости"},
      {"id": 1, "name": "Полная занятость"},
      {"id": 2, "name": "Частичная занятость"},
      {"id": 3, "name": "Проектная работа"},
      {"id": 4, "name": "Стажировка"}
    ],

    [
      {"id": 0, "name": "График работы"},
      {"id": 1, "name": "Полный день"},
      {"id": 2, "name": "Сменный график"},
      {"id": 3, "name": "Вахтовый метод"},
      {"id": 4, "name": "Гибкий график"},
      {"id": 5, "name": "Удаленная работа"}
    ]
]

